vhcs/__init__.py
vhcs/ext/__init__.py
vhcs/ext/ops/__init__.py
vhcs/ext/ops/main.py
hcs_cli_ext_ops-0.1.169.dist-info/METADATA
hcs_cli_ext_ops-0.1.169.dist-info/WHEEL
hcs_cli_ext_ops-0.1.169.dist-info/top_level.txt
hcs_cli_ext_ops-0.1.169.dist-info/RECORD
